Metadata-Version: 2.1
Name: odoo9-addon-l10n-fr-siret
Version: 9.0.1.2.0.99.dev16
Summary: French company identity numbers SIRET/SIREN/NIC
Home-page: UNKNOWN
Author: Numérigraphe,Odoo Community Association (OCA)
Author-email: support@odoo-community.org
License: AGPL-3
Platform: UNKNOWN
Classifier: Programming Language :: Python
Classifier: Framework :: Odoo
Classifier: License :: OSI Approved :: GNU Affero General Public License v3
Requires-Python: ~=2.7
Requires-Dist: odoo (<9.1a,>=9.0a)
